fast_diff_match.cpython-37m-darwin.so
tests/__init__.py
tests/test_diff.py
tests/test_match.py
fast_diff_match-1.0.2.dist-info/LICENSE
fast_diff_match-1.0.2.dist-info/METADATA
fast_diff_match-1.0.2.dist-info/WHEEL
fast_diff_match-1.0.2.dist-info/top_level.txt
fast_diff_match-1.0.2.dist-info/RECORD
