Metadata-Version: 2.1
Name: fast-diff-match
Version: 1.0.2
Summary: A Python extension module that wraps Google's diff_match_patch C++ implementation for very fast string comparisons. Version 1.0.2 fixes a build issue on Macs.
Home-page: https://github.com/JoshData/diff_match_patch-python
Author: Joshua Tauberer
Author-email: jt@occams.info
License: CC0 (copyright waived)
Keywords: diff compare Google match patch diff_match_patch extension native C fast
Platform: UNKNOWN
Classifier: Programming Language :: Python :: 2
Classifier: Programming Language :: Python :: 2.7
Classifier: Programming Language :: Python :: 3
Classifier: Programming Language :: Python :: 3.4
Classifier: Programming Language :: Python :: 3.5
Classifier: Programming Language :: Python :: 3.6
